flatlatex/__init__.py
flatlatex/conv.py
flatlatex/data.py
flatlatex/latexfuntypes.py
flatlatex/parser.py
flatlatex/transliteration.py
flatlatex/bin/__init__.py
flatlatex/bin/flatlatex.py
flatlatex/tests/__init__.py
flatlatex/tests/test_conv.py
flatlatex/tests/test_data_consistancy.py
flatlatex/tests/test_parser.py
flatlatex-0.15.dist-info/LICENCE
flatlatex-0.15.dist-info/METADATA
flatlatex-0.15.dist-info/WHEEL
flatlatex-0.15.dist-info/entry_points.txt
flatlatex-0.15.dist-info/top_level.txt
flatlatex-0.15.dist-info/RECORD
