Metadata-Version: 2.1
Name: flatlatex
Version: 0.15
Summary: A LaTeX math converter to unicode text
Home-page: https://github.com/jb-leger/flatlatex
Author: Jean-Benoist Leger
Author-email: jb@leger.tf
License: BSD-2
Keywords: latex math unicode
Platform: UNKNOWN
Classifier: Development Status :: 3 - Alpha
Classifier: Intended Audience :: Science/Research
Classifier: Topic :: Text Processing :: Markup :: LaTeX
Classifier: License :: OSI Approved
Classifier: Programming Language :: Python :: 3 :: Only
Requires-Python: >=3
Requires-Dist: regex
Provides-Extra: test
Requires-Dist: pytest ; extra == 'test'
